satqubolib/__init__.py
satqubolib/formula.py
satqubolib/generators.py
satqubolib/transformations.py
satqubolib-0.1.0.dist-info/METADATA
satqubolib-0.1.0.dist-info/WHEEL
satqubolib-0.1.0.dist-info/top_level.txt
satqubolib-0.1.0.dist-info/RECORD
